{
  "is_struct": false,
  "key": "",
  "semantic": "ouid| |pettOrg",
  "name": "PFSXRequest",
  "caption": "(МВД) Запрос сведений из органа, производящего выплату пенсии, о прекращении выплаты или неполучении пенсии за выслугу лет",
  "ancestor": "FederalService",
  "container": null,
  "creationTracker": "",
  "changeTracker": "",
  "properties": [
    {
      "order_number": 281,
      "name": "docType",
      "caption": "Вид",
      "type": 0,
      "size": null,
      "decimals": null,
      "nullable": true,
      "readonly": false,
      "indexed": false,
      "unique": false,
      "autoassigned": false,
      "default_value": null,
      "ref_class": null,
      "items_class": null,
      "back_ref": null,
      "binding": null,
      "sel_conditions": [],
      "sel_sorting": [],
      "selection": null,
      "selectall": true,
      "role_permissions": [],
      "index_search": false
    },
    {
      "order_number": 441,
      "name": "reasonlink",
      "caption": "Код госуслуги",
      "type": 0,
      "size": null,
      "decimals": null,
      "nullable": true,
      "readonly": false,
      "indexed": false,
      "unique": false,
      "autoassigned": false,
      "default_value": null,
      "ref_class": null,
      "items_class": null,
      "back_ref": null,
      "binding": null,
      "sel_conditions": [],
      "sel_sorting": [],
      "selection": null,
      "selectall": true,
      "role_permissions": [],
      "index_search": false
    },
    {
      "order_number": 121,
      "name": "STATUSDESCR",
      "caption": "Описание статуса обработки",
      "type": 0,
      "size": null,
      "decimals": null,
      "nullable": true,
      "readonly": false,
      "indexed": false,
      "unique": false,
      "autoassigned": false,
      "default_value": null,
      "ref_class": null,
      "items_class": null,
      "back_ref": null,
      "binding": null,
      "sel_conditions": [],
      "sel_sorting": [],
      "selection": null,
      "selectall": true,
      "role_permissions": [],
      "index_search": false
    },
    {
      "order_number": 151,
      "name": "ERROR_NAME",
      "caption": "Описание кода возврата",
      "type": 0,
      "size": null,
      "decimals": null,
      "nullable": true,
      "readonly": false,
      "indexed": false,
      "unique": false,
      "autoassigned": false,
      "default_value": null,
      "ref_class": null,
      "items_class": null,
      "back_ref": null,
      "binding": null,
      "sel_conditions": [],
      "sel_sorting": [],
      "selection": null,
      "selectall": true,
      "role_permissions": [],
      "index_search": false
    },
    {
      "order_number": 341,
      "name": "formDate",
      "caption": "Дата формирования",
      "type": 9,
      "size": null,
      "decimals": null,
      "nullable": true,
      "readonly": false,
      "indexed": false,
      "unique": false,
      "autoassigned": false,
      "default_value": null,
      "ref_class": null,
      "items_class": null,
      "back_ref": null,
      "binding": null,
      "sel_conditions": [],
      "sel_sorting": [],
      "selection": null,
      "selectall": true,
      "role_permissions": [],
      "index_search": false
    },
    {
      "order_number": 371,
      "name": "rejectInfo",
      "caption": "Причина отказа",
      "type": 0,
      "size": null,
      "decimals": null,
      "nullable": true,
      "readonly": false,
      "indexed": false,
      "unique": false,
      "autoassigned": false,
      "default_value": null,
      "ref_class": null,
      "items_class": null,
      "back_ref": null,
      "binding": null,
      "sel_conditions": [],
      "sel_sorting": [],
      "selection": null,
      "selectall": true,
      "role_permissions": [],
      "index_search": false
    },
    {
      "order_number": 31,
      "name": "FIRST_NAME",
      "caption": "Имя",
      "type": 0,
      "size": null,
      "decimals": null,
      "nullable": true,
      "readonly": false,
      "indexed": false,
      "unique": false,
      "autoassigned": false,
      "default_value": null,
      "ref_class": null,
      "items_class": null,
      "back_ref": null,
      "binding": null,
      "sel_conditions": [],
      "sel_sorting": [],
      "selection": null,
      "selectall": true,
      "role_permissions": [],
      "index_search": false
    },
    {
      "order_number": 421,
      "name": "initialRegNumber",
      "caption": "initialRegNumber",
      "type": 0,
      "size": null,
      "decimals": null,
      "nullable": true,
      "readonly": false,
      "indexed": false,
      "unique": false,
      "autoassigned": false,
      "default_value": null,
      "ref_class": null,
      "items_class": null,
      "back_ref": null,
      "binding": null,
      "sel_conditions": [],
      "sel_sorting": [],
      "selection": null,
      "selectall": true,
      "role_permissions": [],
      "index_search": false
    },
    {
      "order_number": 41,
      "name": "PATRONYMIC",
      "caption": "Отчество",
      "type": 0,
      "size": null,
      "decimals": null,
      "nullable": true,
      "readonly": false,
      "indexed": false,
      "unique": false,
      "autoassigned": false,
      "default_value": null,
      "ref_class": null,
      "items_class": null,
      "back_ref": null,
      "binding": null,
      "sel_conditions": [],
      "sel_sorting": [],
      "selection": null,
      "selectall": true,
      "role_permissions": [],
      "index_search": false
    },
    {
      "order_number": 266,
      "name": "birthDate",
      "caption": "Дата рождения",
      "type": 0,
      "size": null,
      "decimals": null,
      "nullable": true,
      "readonly": false,
      "indexed": false,
      "unique": false,
      "autoassigned": false,
      "default_value": null,
      "ref_class": null,
      "items_class": null,
      "back_ref": null,
      "binding": null,
      "sel_conditions": [],
      "sel_sorting": [],
      "selection": null,
      "selectall": true,
      "role_permissions": [],
      "index_search": false
    },
    {
      "order_number": 91,
      "name": "signature",
      "caption": "Электронно цифровая подпись",
      "type": 14,
      "size": null,
      "decimals": null,
      "nullable": true,
      "readonly": false,
      "indexed": false,
      "unique": false,
      "autoassigned": false,
      "default_value": null,
      "ref_class": null,
      "items_class": "sedECP",
      "back_ref": null,
      "binding": null,
      "sel_conditions": [],
      "sel_sorting": [],
      "selection": null,
      "selectall": true,
      "role_permissions": [],
      "index_search": false
    },
    {
      "order_number": 11,
      "name": "TYPE_QUERY",
      "caption": "Тип запроса",
      "type": 0,
      "size": null,
      "decimals": null,
      "nullable": true,
      "readonly": false,
      "indexed": false,
      "unique": false,
      "autoassigned": false,
      "default_value": null,
      "ref_class": null,
      "items_class": null,
      "back_ref": null,
      "binding": null,
      "sel_conditions": [],
      "sel_sorting": [],
      "selection": null,
      "selectall": true,
      "role_permissions": [],
      "index_search": false
    },
    {
      "order_number": 131,
      "name": "QRYNMB",
      "caption": "Идентификатор заявки",
      "type": 0,
      "size": null,
      "decimals": null,
      "nullable": true,
      "readonly": false,
      "indexed": false,
      "unique": false,
      "autoassigned": false,
      "default_value": null,
      "ref_class": null,
      "items_class": null,
      "back_ref": null,
      "binding": null,
      "sel_conditions": [],
      "sel_sorting": [],
      "selection": null,
      "selectall": true,
      "role_permissions": [],
      "index_search": false
    },
    {
      "order_number": 411,
      "name": "regTime",
      "caption": "regTime",
      "type": 9,
      "size": null,
      "decimals": null,
      "nullable": true,
      "readonly": false,
      "indexed": false,
      "unique": false,
      "autoassigned": false,
      "default_value": null,
      "ref_class": null,
      "items_class": null,
      "back_ref": null,
      "binding": null,
      "sel_conditions": [],
      "sel_sorting": [],
      "selection": null,
      "selectall": true,
      "role_permissions": [],
      "index_search": false
    },
    {
      "order_number": 0,
      "name": "code",
      "caption": "Код информационной системы-отправителя",
      "type": 0,
      "size": null,
      "decimals": null,
      "nullable": true,
      "readonly": false,
      "indexed": false,
      "unique": false,
      "autoassigned": false,
      "default_value": null,
      "ref_class": null,
      "items_class": null,
      "back_ref": null,
      "binding": null,
      "sel_conditions": [],
      "sel_sorting": [],
      "selection": null,
      "selectall": true,
      "role_permissions": [],
      "index_search": false
    },
    {
      "order_number": 291,
      "name": "docNum",
      "caption": "Номер",
      "type": 0,
      "size": null,
      "decimals": null,
      "nullable": true,
      "readonly": false,
      "indexed": false,
      "unique": false,
      "autoassigned": false,
      "default_value": null,
      "ref_class": null,
      "items_class": null,
      "back_ref": null,
      "binding": null,
      "sel_conditions": [],
      "sel_sorting": [],
      "selection": null,
      "selectall": true,
      "role_permissions": [],
      "index_search": false
    },
    {
      "order_number": 301,
      "name": "depRegion",
      "caption": "Регион подразделения",
      "type": 16,
      "size": null,
      "decimals": null,
      "nullable": true,
      "readonly": false,
      "indexed": false,
      "unique": false,
      "autoassigned": false,
      "default_value": null,
      "ref_class": "sprSubjectFederation",
      "items_class": null,
      "back_ref": null,
      "binding": null,
      "sel_conditions": [],
      "sel_sorting": [],
      "selection": null,
      "selectall": true,
      "role_permissions": [],
      "index_search": false
    },
    {
      "order_number": 71,
      "name": "DATE_OF_BIRTH",
      "caption": "Дата рождения",
      "type": 9,
      "size": null,
      "decimals": null,
      "nullable": true,
      "readonly": false,
      "indexed": false,
      "unique": false,
      "autoassigned": false,
      "default_value": null,
      "ref_class": null,
      "items_class": null,
      "back_ref": null,
      "binding": null,
      "sel_conditions": [],
      "sel_sorting": [],
      "selection": null,
      "selectall": true,
      "role_permissions": [],
      "index_search": false
    },
    {
      "order_number": 261,
      "name": "lastname",
      "caption": "Отчество",
      "type": 0,
      "size": null,
      "decimals": null,
      "nullable": true,
      "readonly": false,
      "indexed": false,
      "unique": false,
      "autoassigned": false,
      "default_value": null,
      "ref_class": null,
      "items_class": null,
      "back_ref": null,
      "binding": null,
      "sel_conditions": [],
      "sel_sorting": [],
      "selection": null,
      "selectall": true,
      "role_permissions": [],
      "index_search": false
    },
    {
      "order_number": 311,
      "name": "depName",
      "caption": "Наименование подразделения",
      "type": 0,
      "size": null,
      "decimals": null,
      "nullable": true,
      "readonly": false,
      "indexed": false,
      "unique": false,
      "autoassigned": false,
      "default_value": null,
      "ref_class": null,
      "items_class": null,
      "back_ref": null,
      "binding": null,
      "sel_conditions": [],
      "sel_sorting": [],
      "selection": null,
      "selectall": true,
      "role_permissions": [],
      "index_search": false
    },
    {
      "order_number": 221,
      "name": "resolution",
      "caption": "Резолюция",
      "type": 0,
      "size": null,
      "decimals": null,
      "nullable": true,
      "readonly": false,
      "indexed": false,
      "unique": false,
      "autoassigned": false,
      "default_value": null,
      "ref_class": null,
      "items_class": null,
      "back_ref": null,
      "binding": null,
      "sel_conditions": [],
      "sel_sorting": [],
      "selection": null,
      "selectall": true,
      "role_permissions": [],
      "index_search": false
    },
    {
      "order_number": 271,
      "name": "insNum",
      "caption": "Страховой номер",
      "type": 0,
      "size": null,
      "decimals": null,
      "nullable": true,
      "readonly": false,
      "indexed": false,
      "unique": false,
      "autoassigned": false,
      "default_value": null,
      "ref_class": null,
      "items_class": null,
      "back_ref": null,
      "binding": null,
      "sel_conditions": [],
      "sel_sorting": [],
      "selection": null,
      "selectall": true,
      "role_permissions": [],
      "index_search": false
    },
    {
      "order_number": 201,
      "name": "fio",
      "caption": "ФИО",
      "type": 0,
      "size": null,
      "decimals": null,
      "nullable": true,
      "readonly": false,
      "indexed": false,
      "unique": false,
      "autoassigned": false,
      "default_value": null,
      "ref_class": null,
      "items_class": null,
      "back_ref": null,
      "binding": null,
      "sel_conditions": [],
      "sel_sorting": [],
      "selection": null,
      "selectall": true,
      "role_permissions": [],
      "index_search": false
    },
    {
      "order_number": 111,
      "name": "caseNumber",
      "caption": "Номер запроса в ведомстве",
      "type": 0,
      "size": null,
      "decimals": null,
      "nullable": true,
      "readonly": false,
      "indexed": false,
      "unique": false,
      "autoassigned": false,
      "default_value": null,
      "ref_class": null,
      "items_class": null,
      "back_ref": null,
      "binding": null,
      "sel_conditions": [],
      "sel_sorting": [],
      "selection": null,
      "selectall": true,
      "role_permissions": [],
      "index_search": false
    },
    {
      "order_number": 91,
      "name": "DOCUMENT_NUMBER",
      "caption": "Номер документа",
      "type": 0,
      "size": null,
      "decimals": null,
      "nullable": true,
      "readonly": false,
      "indexed": false,
      "unique": false,
      "autoassigned": false,
      "default_value": null,
      "ref_class": null,
      "items_class": null,
      "back_ref": null,
      "binding": null,
      "sel_conditions": [],
      "sel_sorting": [],
      "selection": null,
      "selectall": true,
      "role_permissions": [],
      "index_search": false
    },
    {
      "order_number": 101,
      "name": "PENSION_DATE",
      "caption": "Дата, на которую запрашиваются сведения",
      "type": 9,
      "size": null,
      "decimals": null,
      "nullable": true,
      "readonly": false,
      "indexed": false,
      "unique": false,
      "autoassigned": false,
      "default_value": null,
      "ref_class": null,
      "items_class": null,
      "back_ref": null,
      "binding": null,
      "sel_conditions": [],
      "sel_sorting": [],
      "selection": null,
      "selectall": true,
      "role_permissions": [],
      "index_search": false
    },
    {
      "order_number": 461,
      "name": "msg_vid",
      "caption": "msg_vid",
      "type": 0,
      "size": null,
      "decimals": null,
      "nullable": true,
      "readonly": false,
      "indexed": false,
      "unique": false,
      "autoassigned": false,
      "default_value": null,
      "ref_class": null,
      "items_class": null,
      "back_ref": null,
      "binding": null,
      "sel_conditions": [],
      "sel_sorting": [],
      "selection": null,
      "selectall": true,
      "role_permissions": [],
      "index_search": false
    },
    {
      "order_number": 21,
      "name": "SECOND_NAME",
      "caption": "Фамилия",
      "type": 0,
      "size": null,
      "decimals": null,
      "nullable": true,
      "readonly": false,
      "indexed": false,
      "unique": false,
      "autoassigned": false,
      "default_value": null,
      "ref_class": null,
      "items_class": null,
      "back_ref": null,
      "binding": null,
      "sel_conditions": [],
      "sel_sorting": [],
      "selection": null,
      "selectall": true,
      "role_permissions": [],
      "index_search": false
    },
    {
      "order_number": 401,
      "name": "regNumber",
      "caption": "regNumber",
      "type": 0,
      "size": null,
      "decimals": null,
      "nullable": true,
      "readonly": false,
      "indexed": false,
      "unique": false,
      "autoassigned": false,
      "default_value": null,
      "ref_class": null,
      "items_class": null,
      "back_ref": null,
      "binding": null,
      "sel_conditions": [],
      "sel_sorting": [],
      "selection": null,
      "selectall": true,
      "role_permissions": [],
      "index_search": false
    },
    {
      "order_number": 171,
      "name": "name",
      "caption": "Наименование организации",
      "type": 0,
      "size": null,
      "decimals": null,
      "nullable": true,
      "readonly": false,
      "indexed": false,
      "unique": false,
      "autoassigned": false,
      "default_value": null,
      "ref_class": null,
      "items_class": null,
      "back_ref": null,
      "binding": null,
      "sel_conditions": [],
      "sel_sorting": [],
      "selection": null,
      "selectall": true,
      "role_permissions": [],
      "index_search": false
    },
    {
      "order_number": 111,
      "name": "STATUSCODE",
      "caption": "Код статуса обработки",
      "type": 0,
      "size": null,
      "decimals": null,
      "nullable": true,
      "readonly": false,
      "indexed": false,
      "unique": false,
      "autoassigned": false,
      "default_value": null,
      "ref_class": null,
      "items_class": null,
      "back_ref": null,
      "binding": null,
      "sel_conditions": [],
      "sel_sorting": [],
      "selection": null,
      "selectall": true,
      "role_permissions": [],
      "index_search": false
    },
    {
      "order_number": 141,
      "name": "ERROR_CODE",
      "caption": "Код возврата",
      "type": 0,
      "size": null,
      "decimals": null,
      "nullable": true,
      "readonly": false,
      "indexed": false,
      "unique": false,
      "autoassigned": false,
      "default_value": null,
      "ref_class": null,
      "items_class": null,
      "back_ref": null,
      "binding": null,
      "sel_conditions": [],
      "sel_sorting": [],
      "selection": null,
      "selectall": true,
      "role_permissions": [],
      "index_search": false
    },
    {
      "order_number": 351,
      "name": "numPays",
      "caption": "Количество выплат",
      "type": 0,
      "size": null,
      "decimals": null,
      "nullable": true,
      "readonly": false,
      "indexed": false,
      "unique": false,
      "autoassigned": false,
      "default_value": null,
      "ref_class": null,
      "items_class": null,
      "back_ref": null,
      "binding": null,
      "sel_conditions": [],
      "sel_sorting": [],
      "selection": null,
      "selectall": true,
      "role_permissions": [],
      "index_search": false
    },
    {
      "order_number": 81,
      "name": "DOCUMENT_NAME",
      "caption": "Вид документа",
      "type": 0,
      "size": null,
      "decimals": null,
      "nullable": true,
      "readonly": false,
      "indexed": false,
      "unique": false,
      "autoassigned": false,
      "default_value": null,
      "ref_class": null,
      "items_class": null,
      "back_ref": null,
      "binding": null,
      "sel_conditions": [],
      "sel_sorting": [],
      "selection": null,
      "selectall": true,
      "role_permissions": [],
      "index_search": false
    },
    {
      "order_number": 301,
      "name": "fromSystemLink",
      "caption": "Региональная система отправитель",
      "type": 13,
      "size": null,
      "decimals": null,
      "nullable": true,
      "readonly": false,
      "indexed": false,
      "unique": false,
      "autoassigned": false,
      "default_value": null,
      "ref_class": "egOrganization",
      "items_class": null,
      "back_ref": null,
      "binding": null,
      "sel_conditions": [],
      "sel_sorting": [],
      "selection": null,
      "selectall": true,
      "role_permissions": [],
      "index_search": false
    },
    {
      "order_number": 241,
      "name": "secondname",
      "caption": "Фамилия",
      "type": 0,
      "size": null,
      "decimals": null,
      "nullable": true,
      "readonly": false,
      "indexed": false,
      "unique": false,
      "autoassigned": false,
      "default_value": null,
      "ref_class": null,
      "items_class": null,
      "back_ref": null,
      "binding": null,
      "sel_conditions": [],
      "sel_sorting": [],
      "selection": null,
      "selectall": true,
      "role_permissions": [],
      "index_search": false
    },
    {
      "order_number": 251,
      "name": "firstname",
      "caption": "Имя",
      "type": 0,
      "size": null,
      "decimals": null,
      "nullable": true,
      "readonly": false,
      "indexed": false,
      "unique": false,
      "autoassigned": false,
      "default_value": null,
      "ref_class": null,
      "items_class": null,
      "back_ref": null,
      "binding": null,
      "sel_conditions": [],
      "sel_sorting": [],
      "selection": null,
      "selectall": true,
      "role_permissions": [],
      "index_search": false
    },
    {
      "order_number": 61,
      "name": "DPTCODLink",
      "caption": "Регион направления запроса",
      "type": 16,
      "size": null,
      "decimals": null,
      "nullable": true,
      "readonly": false,
      "indexed": false,
      "unique": false,
      "autoassigned": false,
      "default_value": null,
      "ref_class": "sprSubjectFederation",
      "items_class": null,
      "back_ref": null,
      "binding": null,
      "sel_conditions": [],
      "sel_sorting": [],
      "selection": null,
      "selectall": true,
      "role_permissions": [],
      "index_search": false
    },
    {
      "order_number": 161,
      "name": "resultData",
      "caption": "Результат обработки",
      "type": 1,
      "size": null,
      "decimals": null,
      "nullable": true,
      "readonly": false,
      "indexed": false,
      "unique": false,
      "autoassigned": false,
      "default_value": null,
      "ref_class": null,
      "items_class": null,
      "back_ref": null,
      "binding": null,
      "sel_conditions": [],
      "sel_sorting": [],
      "selection": null,
      "selectall": true,
      "role_permissions": [],
      "index_search": false
    },
    {
      "order_number": 51,
      "name": "SNILS",
      "caption": "СНИЛС",
      "type": 0,
      "size": null,
      "decimals": null,
      "nullable": true,
      "readonly": false,
      "indexed": false,
      "unique": false,
      "autoassigned": false,
      "default_value": null,
      "ref_class": null,
      "items_class": null,
      "back_ref": null,
      "binding": null,
      "sel_conditions": [],
      "sel_sorting": [],
      "selection": null,
      "selectall": true,
      "role_permissions": [],
      "index_search": false
    },
    {
      "order_number": 331,
      "name": "datePresence",
      "caption": "Наличие данных",
      "type": 0,
      "size": null,
      "decimals": null,
      "nullable": true,
      "readonly": false,
      "indexed": false,
      "unique": false,
      "autoassigned": false,
      "default_value": null,
      "ref_class": null,
      "items_class": null,
      "back_ref": null,
      "binding": null,
      "sel_conditions": [],
      "sel_sorting": [],
      "selection": null,
      "selectall": true,
      "role_permissions": [],
      "index_search": false
    }
  ],
  "role_permissions": []
}